Workbook

Sheet Cómo usar esto
B2: Iron Savage — datos pendientes para pasar a producción
B4: Qué es | C4: Todo lo que la tienda tiene todavía como dato de plantilla o provisional y hay que sustituir por datos reales antes de abrir al público: datos de la empresa, facturación, dominios, emails, pagos, envíos, textos, imágenes y decisiones de negocio.
B5: Qué hay que rellenar | C5: En la hoja «Datos a rellenar», la columna amarilla «VALOR REAL (a rellenar)» y la columna «Estado». Si algo no aplica, escribir «No aplica» y marcar el estado.
B6: Prioridad | C6: Crítico = sin esto no se puede abrir la tienda (o hay riesgo legal/fiscal). Importante = debería estar el día del lanzamiento. Recomendado = mejora, puede ir después. Informativo = solo para conocimiento.
B7: ¿Quién lo aporta? | C7: Cliente, Gestoría / asesor fiscal, Abogado, Banco o Técnico (el desarrollador). «Cliente + Técnico» = se decide juntos.
B8: Formato o ejemplo | C8: Cómo debe ser el dato. Los ejemplos son inventados: no copiarlos tal cual.
B9: Valor actual (plantilla) | C9: Lo que hay ahora en el proyecto. Casi siempre es un valor de pruebas.
B10: Dónde va | C10: Para el desarrollador: archivo o variable exacta donde se pondrá el dato. «.env.prod» = archivo de configuración del servidor de producción. «Dashboard» = se configura desde el panel de administración, sin programar.
B11: Datos confidenciales | C11: Contraseñas y claves (SMTP, Redsys, administrador) NO se escriben en este Excel: entregarlas por un canal seguro (gestor de contraseñas o en persona).
B12: Otras hojas | C12: «Textos de emails»: asunto y frases de cada email automático, para revisar o reescribir. «Resumen»: recuento automático por prioridad y estado. «Hosting»: requisitos del servidor y proveedores orientativos.
B13: Sustituye a | C13: Este archivo sustituye a «Checklist-Puesta-en-Produccion.xlsx», que quedó desactualizado.
B15: Leyenda
C16: Celda para rellenar por el cliente
C17: Fila de ejemplo (formato esperado)
C18: Prioridad: Crítico
C19: Prioridad: Importante
C20: Prioridad: Recomendado
C21: Prioridad: Informativo

Sheet Resumen
A1: Resumen de datos pendientes
A2: Se actualiza solo al cambiar la columna «Estado» de la hoja «Datos a rellenar» (excluye la fila de ejemplo).
A4: Prioridad | B4: Total | C4: Pendiente | D4: En curso | E4: Hecho | F4: No aplica | G4: % resuelto
A5: Crítico | B5: =COUNTIFS('Datos a rellenar'!$F$3:$F$119,$A5) | C5: =COUNTIFS('Datos a rellenar'!$F$3:$F$119,$A5,'Datos a rellenar'!$J$3:$J$119,"Pendiente") | D5: =COUNTIFS('Datos a rellenar'!$F$3:$F$119,$A5,'Datos a rellenar'!$J$3:$J$119,"En curso") | E5: =COUNTIFS('Datos a rellenar'!$F$3:$F$119,$A5,'Datos a rellenar'!$J$3:$J$119,"Hecho") | F5: =COUNTIFS('Datos a rellenar'!$F$3:$F$119,$A5,'Datos a rellenar'!$J$3:$J$119,"No aplica") | G5: =IF(B5=0,0,(E5+F5)/B5)
A6: Importante | B6: =COUNTIFS('Datos a rellenar'!$F$3:$F$119,$A6) | C6: =COUNTIFS('Datos a rellenar'!$F$3:$F$119,$A6,'Datos a rellenar'!$J$3:$J$119,"Pendiente") | D6: =COUNTIFS('Datos a rellenar'!$F$3:$F$119,$A6,'Datos a rellenar'!$J$3:$J$119,"En curso") | E6: =COUNTIFS('Datos a rellenar'!$F$3:$F$119,$A6,'Datos a rellenar'!$J$3:$J$119,"Hecho") | F6: =COUNTIFS('Datos a rellenar'!$F$3:$F$119,$A6,'Datos a rellenar'!$J$3:$J$119,"No aplica") | G6: =IF(B6=0,0,(E6+F6)/B6)
A7: Recomendado | B7: =COUNTIFS('Datos a rellenar'!$F$3:$F$119,$A7) | C7: =COUNTIFS('Datos a rellenar'!$F$3:$F$119,$A7,'Datos a rellenar'!$J$3:$J$119,"Pendiente") | D7: =COUNTIFS('Datos a rellenar'!$F$3:$F$119,$A7,'Datos a rellenar'!$J$3:$J$119,"En curso") | E7: =COUNTIFS('Datos a rellenar'!$F$3:$F$119,$A7,'Datos a rellenar'!$J$3:$J$119,"Hecho") | F7: =COUNTIFS('Datos a rellenar'!$F$3:$F$119,$A7,'Datos a rellenar'!$J$3:$J$119,"No aplica") | G7: =IF(B7=0,0,(E7+F7)/B7)
A8: Informativo | B8: =COUNTIFS('Datos a rellenar'!$F$3:$F$119,$A8) | C8: =COUNTIFS('Datos a rellenar'!$F$3:$F$119,$A8,'Datos a rellenar'!$J$3:$J$119,"Pendiente") | D8: =COUNTIFS('Datos a rellenar'!$F$3:$F$119,$A8,'Datos a rellenar'!$J$3:$J$119,"En curso") | E8: =COUNTIFS('Datos a rellenar'!$F$3:$F$119,$A8,'Datos a rellenar'!$J$3:$J$119,"Hecho") | F8: =COUNTIFS('Datos a rellenar'!$F$3:$F$119,$A8,'Datos a rellenar'!$J$3:$J$119,"No aplica") | G8: =IF(B8=0,0,(E8+F8)/B8)
A9: TOTAL | B9: =SUM(B5:B8) | C9: =SUM(C5:C8) | D9: =SUM(D5:D8) | E9: =SUM(E5:E8) | F9: =SUM(F5:F8) | G9: =IF(B9=0,0,(E9+F9)/B9)
A11: Pendientes por área
A12: Área | B12: Total | C12: Pendiente | D12: Críticos pendientes
A13: Empresa y datos legales | B13: =COUNTIFS('Datos a rellenar'!$B$3:$B$119,$A13) | C13: =COUNTIFS('Datos a rellenar'!$B$3:$B$119,$A13,'Datos a rellenar'!$J$3:$J$119,"Pendiente") | D13: =COUNTIFS('Datos a rellenar'!$B$3:$B$119,$A13,'Datos a rellenar'!$J$3:$J$119,"Pendiente",'Datos a rellenar'!$F$3:$F$119,"Crítico")
A14: Textos legales: decisiones y revisión | B14: =COUNTIFS('Datos a rellenar'!$B$3:$B$119,$A14) | C14: =COUNTIFS('Datos a rellenar'!$B$3:$B$119,$A14,'Datos a rellenar'!$J$3:$J$119,"Pendiente") | D14: =COUNTIFS('Datos a rellenar'!$B$3:$B$119,$A14,'Datos a rellenar'!$J$3:$J$119,"Pendiente",'Datos a rellenar'!$F$3:$F$119,"Crítico")
A15: Facturación y fiscalidad | B15: =COUNTIFS('Datos a rellenar'!$B$3:$B$119,$A15) | C15: =COUNTIFS('Datos a rellenar'!$B$3:$B$119,$A15,'Datos a rellenar'!$J$3:$J$119,"Pendiente") | D15: =COUNTIFS('Datos a rellenar'!$B$3:$B$119,$A15,'Datos a rellenar'!$J$3:$J$119,"Pendiente",'Datos a rellenar'!$F$3:$F$119,"Crítico")
A16: Dominios, servidor y despliegue | B16: =COUNTIFS('Datos a rellenar'!$B$3:$B$119,$A16) | C16: =COUNTIFS('Datos a rellenar'!$B$3:$B$119,$A16,'Datos a rellenar'!$J$3:$J$119,"Pendiente") | D16: =COUNTIFS('Datos a rellenar'!$B$3:$B$119,$A16,'Datos a rellenar'!$J$3:$J$119,"Pendiente",'Datos a rellenar'!$F$3:$F$119,"Crítico")
A17: Correo electrónico (emails automáticos) | B17: =COUNTIFS('Datos a rellenar'!$B$3:$B$119,$A17) | C17: =COUNTIFS('Datos a rellenar'!$B$3:$B$119,$A17,'Datos a rellenar'!$J$3:$J$119,"Pendiente") | D17: =COUNTIFS('Datos a rellenar'!$B$3:$B$119,$A17,'Datos a rellenar'!$J$3:$J$119,"Pendiente",'Datos a rellenar'!$F$3:$F$119,"Crítico")
A18: Pagos con tarjeta (Redsys) | B18: =COUNTIFS('Datos a rellenar'!$B$3:$B$119,$A18) | C18: =COUNTIFS('Datos a rellenar'!$B$3:$B$119,$A18,'Datos a rellenar'!$J$3:$J$119,"Pendiente") | D18: =COUNTIFS('Datos a rellenar'!$B$3:$B$119,$A18,'Datos a rellenar'!$J$3:$J$119,"Pendiente",'Datos a rellenar'!$F$3:$F$119,"Crítico")
A19: Accesos y claves internas | B19: =COUNTIFS('Datos a rellenar'!$B$3:$B$119,$A19) | C19: =COUNTIFS('Datos a rellenar'!$B$3:$B$119,$A19,'Datos a rellenar'!$J$3:$J$119,"Pendiente") | D19: =COUNTIFS('Datos a rellenar'!$B$3:$B$119,$A19,'Datos a rellenar'!$J$3:$J$119,"Pendiente",'Datos a rellenar'!$F$3:$F$119,"Crítico")
A20: Envíos y logística | B20: =COUNTIFS('Datos a rellenar'!$B$3:$B$119,$A20) | C20: =COUNTIFS('Datos a rellenar'!$B$3:$B$119,$A20,'Datos a rellenar'!$J$3:$J$119,"Pendiente") | D20: =COUNTIFS('Datos a rellenar'!$B$3:$B$119,$A20,'Datos a rellenar'!$J$3:$J$119,"Pendiente",'Datos a rellenar'!$F$3:$F$119,"Crítico")
A21: Textos de la tienda (marketing) | B21: =COUNTIFS('Datos a rellenar'!$B$3:$B$119,$A21) | C21: =COUNTIFS('Datos a rellenar'!$B$3:$B$119,$A21,'Datos a rellenar'!$J$3:$J$119,"Pendiente") | D21: =COUNTIFS('Datos a rellenar'!$B$3:$B$119,$A21,'Datos a rellenar'!$J$3:$J$119,"Pendiente",'Datos a rellenar'!$F$3:$F$119,"Crítico")
A22: Marca e imágenes | B22: =COUNTIFS('Datos a rellenar'!$B$3:$B$119,$A22) | C22: =COUNTIFS('Datos a rellenar'!$B$3:$B$119,$A22,'Datos a rellenar'!$J$3:$J$119,"Pendiente") | D22: =COUNTIFS('Datos a rellenar'!$B$3:$B$119,$A22,'Datos a rellenar'!$J$3:$J$119,"Pendiente",'Datos a rellenar'!$F$3:$F$119,"Crítico")
A23: Analítica (Google Analytics 4) | B23: =COUNTIFS('Datos a rellenar'!$B$3:$B$119,$A23) | C23: =COUNTIFS('Datos a rellenar'!$B$3:$B$119,$A23,'Datos a rellenar'!$J$3:$J$119,"Pendiente") | D23: =COUNTIFS('Datos a rellenar'!$B$3:$B$119,$A23,'Datos a rellenar'!$J$3:$J$119,"Pendiente",'Datos a rellenar'!$F$3:$F$119,"Crítico")
A24: Catálogo y contenido | B24: =COUNTIFS('Datos a rellenar'!$B$3:$B$119,$A24) | C24: =COUNTIFS('Datos a rellenar'!$B$3:$B$119,$A24,'Datos a rellenar'!$J$3:$J$119,"Pendiente") | D24: =COUNTIFS('Datos a rellenar'!$B$3:$B$119,$A24,'Datos a rellenar'!$J$3:$J$119,"Pendiente",'Datos a rellenar'!$F$3:$F$119,"Crítico")
... A26: Copias de seguridad | B26: =COUNTIFS('Datos a rellenar'!$B$3:$B$119,$A26) | C26: =COUNTIFS('Datos a rellenar'!$B$3:$B$119,$A26,'Datos a rellenar'!$J$3:$J$119,"Pendiente") | D26: =COUNTIFS('Datos a rellenar'!$B$3:$B$119,$A26,'Datos a rellenar'!$J$3:$J$119,"Pendiente",'Datos a rellenar'!$F$3:$F$119,"Crítico")

Sheet Datos a rellenar
A1: Nº | B1: Área | C1: Qué se necesita | D1: Para qué sirve / explicación | E1: Formato o ejemplo esperado | F1: Prioridad | G1: Valor actual (plantilla) | H1: ¿Quién lo aporta? | I1: VALOR REAL (a rellenar) | J1: Estado | K1: Dónde va (para el técnico) | L1: Notas
A2: Ej. | B2: (ejemplo) | C2: Email de atención al cliente | D2: Dirección donde escriben los clientes. | E2: hola@ironsavage.es | F2: Crítico | G2: [EMAIL DE ATENCIÓN AL CLIENTE] | H2: Cliente | I2: hola@ironsavage.es | J2: Hecho | K2: apps/storefront/src/config/company.ts → COMPANY.contactEmail | L2: Fila de ejemplo: no forma parte de la lista.
B3: A. Empresa y datos legales
A4: 1 | B4: Empresa y datos legales | C4: Razón social o nombre del titular | D4: Nombre legal exacto de quien vende. Aparece en el aviso legal, la privacidad, los términos, envíos y devoluciones, accesibilidad, IA y en el aviso de privacidad del registro. | E4: Iron Savage Nutrition, S.L. (o nombre y apellidos si es autónomo) | F4: Crítico | G4: [RAZÓN SOCIAL O NOMBRE DEL TITULAR] resaltado en amarillo en la web | H4: Cliente | J4: Pendiente | K4: apps/storefront/src/config/company.ts → COMPANY.legalName | L4: Se rellena una vez y cambia en todas las páginas.
A5: 2 | B5: Empresa y datos legales | C5: NIF / CIF | D5: Identificación fiscal del titular (obligatoria en el aviso legal, LSSI-CE art. 10). | E5: B12345678 | F5: Crítico | G5: [NIF/CIF] | H5: Cliente | J5: Pendiente | K5: apps/storefront/src/config/company.ts → COMPANY.taxId
A6: 3 | B6: Empresa y datos legales | C6: Domicilio social | D6: Dirección registrada del titular. | E6: Calle Mayor 1, 2º B, 28013 Madrid | F6: Crítico | G6: [DOMICILIO SOCIAL COMPLETO] | H6: Cliente | J6: Pendiente | K6: apps/storefront/src/config/company.ts → COMPANY.address | L6: También se usa como dirección postal para reclamaciones y derechos RGPD.
A7: 4 | B7: Empresa y datos legales | C7: Datos del Registro Mercantil | D7: Obligatorio si es una sociedad (S.L., S.A.). Si es autónomo, no aplica. | E7: Inscrita en el Registro Mercantil de Madrid, Tomo 1234, Folio 56, Hoja M-78901 | F7: Crítico | G7: [DATOS REGISTRALES…] | H7: Cliente | J7: Pendiente | K7: apps/storefront/src/config/company.ts → COMPANY.registry | L7: Poner «No aplica» si es autónomo.
A8: 5 | B8: Empresa y datos legales | C8: Email de atención al cliente | D8: Dirección donde escriben los clientes (dudas, devoluciones, reclamaciones, accesibilidad). | E8: hola@ironsavage.es | F8: Crítico | G8: [EMAIL DE ATENCIÓN AL CLIENTE] | H8: Cliente | J8: Pendiente | K8: apps/storefront/src/config/company.ts → COMPANY.contactEmail | L8: Debe ser un buzón que alguien lea.
A9: 6 | B9: Empresa y datos legales | C9: Email de protección de datos | D9: Para ejercer derechos RGPD (acceso, supresión…). Puede ser el mismo que el de atención al cliente. | E9: privacidad@ironsavage.es | F9: Crítico | G9: [EMAIL DE PROTECCIÓN DE DATOS] | H9: Cliente | J9: Pendiente | K9: apps/storefront/src/config/company.ts → COMPANY.privacyEmail
A10: 7 | B10: Empresa y datos legales | C10: Teléfono de contacto | D10: La ley exige un medio de contacto directo y efectivo; el teléfono es lo habitual. | E10: +34 600 000 000 | F10: Importante | G10: [TELÉFONO DE CONTACTO] | H10: Cliente | J10: Pendiente | K10: apps/storefront/src/config/company.ts → COMPANY.phone
A11: 8 | B11: Empresa y datos legales | C11: Registro sanitario (RGSEAA) o comunicación | D11: Las empresas que comercializan complementos alimenticios deben estar inscritas o haber comunicado su actividad a Sanidad. | E11: Nº RGSEAA 26.012345/M (o «No aplica») | F11: Importante | G11: [Nº DE REGISTRO SANITARIO…] | H11: Cliente | J11: Pendiente | K11: apps/storefront/src/config/company.ts → COMPANY.healthRegistry | L11: Confirmar con un consultor sanitario si aplica.
A12: 9 | B12: Empresa y datos legales | C12: Delegado de protección de datos (DPD) | D12: Solo obligatorio en algunos casos. Si no se ha designado, indicarlo. | E12: No designado (o nombre + email) | F12: Recomendado | G12: [DELEGADO DE PROTECCIÓN DE DATOS…] | H12: Cliente | J12: Pendiente | K12: apps/storefront/src/config/company.ts → COMPANY.dpo
A13: 10 | B13: Empresa y datos legales | C13: Proveedor de hosting y país | D13: Aparece como destinatario de datos en la política de privacidad. | E13: Hetzner Online GmbH (Alemania) | F13: Importante | G13: [PROVEEDOR DE HOSTING Y PAÍS] | H13: Cliente + Técnico | J13: Pendiente | K13: apps/storefront/src/config/company.ts → COMPANY.hostingProvider | L13: Se decide al contratar el servidor (hoja «Hosting»).
A14: 11 | B14: Empresa y datos legales | C14: Proveedor de envío de emails y país | D14: Aparece como destinatario de datos en la política de privacidad. | E14: Brevo (Francia) | F14: Importante | G14: [PROVEEDOR DE ENVÍO DE EMAILS Y PAÍS] | H14: Cliente + Técnico | J14: Pendiente | K14: apps/storefront/src/config/company.ts → COMPANY.emailProvider | L14: Ver sección E.
A15: 12 | B15: Empresa y datos legales | C15: Empresas de transporte | D15: Aparecen en la política de privacidad y en envíos y devoluciones. | E15: Correos Express y SEUR | F15: Importante | G15: [EMPRESAS DE TRANSPORTE] | H15: Cliente | J15: Pendiente | K15: apps/storefront/src/config/company.ts → COMPANY.carriers
A16: 13 | B16: Empresa y datos legales | C16: Dirección para devoluciones | D16: A dónde envía el cliente los productos devueltos. | E16: Almacén Iron Savage, Pol. Ind. X, nave 3, 28906 Getafe (Madrid) | F16: Crítico | G16: [DIRECCIÓN PARA DEVOLUCIONES] | H16: Cliente | J16: Pendiente | K16: apps/storefront/src/config/company.ts → COMPANY.returnsAddress | L16: Puede coincidir con el domicilio social.
A17: 14 | B17: Empresa y datos legales | C17: Plazos de entrega | D17: Plazo estimado desde que se confirma el pago (se muestra en envíos y devoluciones). | E17: 24-72 h laborables en península; 3-5 días laborables en Baleares | F17: Crítico | G17: [PLAZOS DE ENTREGA] | H17: Cliente | J17: Pendiente | K17: apps/storefront/src/config/company.ts → COMPANY.deliveryTimes | L17: Nunca más de 30 días (límite legal).
A18: 15 | B18: Empresa y datos legales | C18: Quién paga la devolución por desistimiento | D18: La ley obliga a informar de quién asume el coste; si no se informa, lo paga la tienda. | E18: El cliente, con un coste aproximado de 5 € (o «Gratuita») | F18: Crítico | G18: [QUIÉN ASUME EL COSTE DE LA DEVOLUCIÓN] | H18: Cliente | J18: Pendiente | K18: apps/storefront/src/config/company.ts → COMPANY.returnCosts
A19: 16 | B19: Empresa y datos legales | C19: Entidad de resolución de conflictos / arbitraje de consumo | D19: Hay que informar si la empresa está adherida a alguna (o que no lo está). | E19: No estamos adheridos a ningún sistema de resolución alternativa (o «Junta Arbitral de Consumo de …») | F19: Importante | G19: [ENTIDAD DE RESOLUCIÓN ALTERNATIVA…] | H19: Cliente | J19: Pendiente | K19: apps/storefront/src/config/company.ts → COMPANY.adrEntity
B20: B. Textos legales: decisiones y revisión
A21: 17 | B21: Textos legales: decisiones y revisión | C21: Revisión de los textos legales por un abogado | D21: Aviso legal, términos, privacidad, cookies, envíos y devoluciones, IA y accesibilidad están redactados conforme a la normativa española, pero deben revisarse antes de publicar. | E21: OK del abogado (fecha) | F21: Crítico | G21: Borrador con aviso «pendiente de revisión legal» | H21: Abogado | J21: Pendiente | K21: apps/storefront/src/site/legal/*.tsx
A22: 18 | B22: Textos legales: decisiones y revisión | C22: Edad mínima para crear una cuenta | D22: Los términos dicen hoy «mayor de 18 años». | E22: 18 años (o la que decida el cliente; nunca menos de 14 por RGPD) | F22: Importante | G22: 18 años | H22: Cliente | J22: Pendiente | K22: terminos-y-condiciones.tsx §3 y politica-de-privacidad.tsx
A23: 19 | B23: Textos legales: decisiones y revisión | C23: Qué contenidos se han creado con IA | D23: Transparencia exigida: indicar si textos, imágenes o traducciones de la tienda se han generado con IA. | E23: Descripciones de producto redactadas con IA y revisadas por el equipo; imágenes: ninguna | F23: Importante | G23: [INDICAR QUÉ CONTENIDOS SE HAN GENERADO CON IA…] | H23: Cliente | J23: Pendiente | K23: apps/storefront/src/site/legal/uso-de-inteligencia-artificial.tsx
A24: 20 | B24: Textos legales: decisiones y revisión | C24: ¿La empresa es microempresa? | D24: Menos de 10 empleados y facturación ≤ 2 M€: queda exenta de la Ley 11/2023 de accesibilidad (la tienda ya cumple igualmente). | E24: Sí / No | F24: Informativo | G24: — | H24: Cliente | J24: Pendiente | K24: docs/legal.md (accesibilidad) | L24: Solo informativo; la declaración de accesibilidad ya está publicada.
A25: 21 | B25: Textos legales: decisiones y revisión | C25: Barreras de accesibilidad conocidas | D25: Si una revisión manual (lector de pantalla) detecta problemas, se anotan en la declaración con su alternativa. | E25: Ninguna conocida (o lista de barreras + fecha de solución) | F25: Recomendado | G25: [AÑADIR AQUÍ LAS BARRERAS…] | H25: Cliente + Técnico | J25: Pendiente | K25: apps/storefront/src/site/legal/accesibilidad.tsx
A26: 22 | B26: Textos legales: decisiones y revisión | C26: ¿Se enviarán newsletters / comunicaciones comerciales? | D26: La privacidad contempla esta posibilidad, pero hoy la tienda no tiene newsletter ni casilla para suscribirse. | E26: No por ahora (o «Sí» → hay que desarrollar la suscripción con consentimiento) | F26: Recomendado | G26: No existe | H26: Cliente | J26: Pendiente | K26: — | L26: Si es «Sí», requiere desarrollo.
A27: 23 | B27: Textos legales: decisiones y revisión | C27: Hojas oficiales de queja y reclamación | D27: Obligatorio tenerlas a disposición del consumidor; el modelo depende de la comunidad autónoma. | E27: Modelo oficial de la Comunidad de Madrid, en PDF | F27: Importante | G27: Los términos indican que se solicitan por email | H27: Cliente | J27: Pendiente | K27: —
A28: 24 | B28: Textos legales: decisiones y revisión | C28: Excepciones al desistimiento | D28: Los textos excluyen del desistimiento los productos con el precinto abierto (salud e higiene). Confirmar que aplica a todo el catálogo. | E28: Confirmado / cambios | F28: Importante | G28: Productos desprecintados excluidos | H28: Abogado | J28: Pendiente | K28: terminos-y-condiciones.tsx §9 y envios-y-devoluciones.tsx §3
A29: 25 | B29: Textos legales: decisiones y revisión | C29: Quitar el aviso «Borrador — pendiente de revisión legal» | D29: Cuando no quede ningún dato resaltado y el abogado haya dado el visto bueno. | E29: Hecho | F29: Crítico | G29: Visible en todas las páginas legales | H29: Técnico | J29: Pendiente | K29: apps/storefront/src/site/legal/legal-page.tsx
A30: 26 | B30: Textos legales: decisiones y revisión | C30: Versión (fecha) de los textos legales | D30: Fecha de «Última actualización» y versión que se guarda en cada pedido al aceptar los términos. | E30: 2026-10-15 | F30: Informativo | G30: 2026-09-28 | H30: Técnico | J30: Pendiente | K30: apps/storefront/src/config/legal.ts → LEGAL_VERSION | L30: Actualizar cada vez que cambie un texto legal.
B31: C. Facturación y fiscalidad
A32: 27 | B32: Facturación y fiscalidad | C32: Razón social en las facturas | D32: Nombre fiscal exacto del emisor de la factura. | E32: Iron Savage Nutrition, S.L. | F32: Crítico | G32: Tienda Suple (placeholder) | H32: Cliente | J32: Pendiente | K32: .env.prod → INVOICE_STORE_NAME | L32: Si no se rellena, las facturas dicen «Razón social pendiente de configurar».
A33: 28 | B33: Facturación y fiscalidad | C33: NIF/CIF en las facturas | E33: B12345678 | F33: Crítico | G33: B00000000 | H33: Cliente | J33: Pendiente | K33: .env.prod → INVOICE_STORE_TAX_ID
A34: 29 | B34: Facturación y fiscalidad | C34: Dirección fiscal en las facturas | E34: Calle Mayor 1, 2º B, 28013 Madrid, España | F34: Crítico | G34: Calle Ejemplo 1, 28001 Madrid, España | H34: Cliente | J34: Pendiente | K34: .env.prod → INVOICE_STORE_ADDRESS
A35: 30 | B35: Facturación y fiscalidad | C35: Email en las facturas | E35: facturacion@ironsavage.es | F35: Importante | G35: facturacion@example.com | H35: Cliente | J35: Pendiente | K35: .env.prod → INVOICE_STORE_EMAIL
A36: 31 | B36: Facturación y fiscalidad | C36: Teléfono en las facturas (opcional) | D36: Solo aparece si se rellena. | E36: +34 600 000 000 | F36: Recomendado | G36: (vacío) | H36: Cliente | J36: Pendiente | K36: .env.prod → INVOICE_STORE_PHONE
A37: 32 | B37: Facturación y fiscalidad | C37: Datos del Registro Mercantil en las facturas | D37: Obligatorio en las facturas de una sociedad (art. 24 del Reglamento del Registro Mercantil). | E37: Inscrita en el R.M. de Madrid, Tomo 1234, Folio 56, Hoja M-78901 | F37: Crítico | G37: (vacío) | H37: Cliente | J37: Pendiente | K37: .env.prod → INVOICE_STORE_REGISTRY | L37: Dejar vacío si es autónomo.
A38: 33 | B38: Facturación y fiscalidad | C38: Tipo de IVA de los productos | D38: Ya están creadas las categorías General 21 %, Reducido 10 % y Superreducido 4 %. Falta decidir cuál lleva cada producto; por defecto, General. Los complementos alimenticios suelen tributar al 10 %. | E38: Proteínas y creatinas: Reducido (10 %); shakers y ropa: General (21 %) | F38: Crítico | G38: General 21 % para todo (categorías 10 % y 4 % ya disponibles) | H38: Gestoría / asesor fiscal | J38: Pendiente | K38: Dashboard → Catálogo → producto → variante → Categoría de impuesto | L38: Afecta al precio final y a las facturas. Ver docs/iva-envios-facturacion.md.
A39: 34 | B39: Facturación y fiscalidad | C39: ¿Se vende a Canarias, Ceuta y Melilla? | D39: Ya está preparado: esos pedidos se detectan por código postal y van sin IVA español (zona «Canarias, Ceuta y Melilla»). Hoy no se puede comprar desde allí hasta que se marque el territorio en un método de envío. | E39: No / Sí → marcar «Islas Canarias» (etc.) en un método de envío con su tarifa | F39: Importante | G39: No se envía (preparado) | H39: Gestoría / asesor fiscal | J39: Pendiente | K39: Dashboard → Ajustes → Métodos de envío → condición «Territorios de España y pedido mínimo» | L39: Confirmar también la mención de exención que imprime la factura (fila siguiente).
A40: 35 | B40: Facturación y fiscalidad | C40: Mención de exención en facturas a Canarias, Ceuta y Melilla | D40: Las facturas con líneas al 0 % imprimen: «Operación exenta de IVA (art. 21 de la Ley 37/1992): entrega de bienes con destino a Canarias, Ceuta o Melilla». | E40: Texto confirmado o corregido | F40: Importante | G40: Texto provisional | H40: Gestoría / asesor fiscal | J40: Pendiente | K40: apps/server/src/plugins/invoicing/invoice-pdf.generator.ts
A41: 36 | B41: Facturación y fiscalidad | C41: Veri*Factu (sistema de facturación verificable) | D41: Punto de enganche listo: cada factura se entrega a un «proveedor fiscal», y su QR y leyenda se imprimen en el PDF. Falta elegir cómo certificarse (proveedor homologado con API o software propio) y escribir el adaptador. | E41: Proveedor elegido + credenciales de su API | F41: Crítico | G41: Enganche preparado, sin proveedor | H41: Gestoría / asesor fiscal | J41: Pendiente | K41: apps/server/src/plugins/invoicing/types.ts (FiscalRegistrationProvider) + vendure-config.ts | L41: Desarrollo pequeño una vez elegido el proveedor. Obligatorio previsiblemente en 2027: confirmar fechas.
A42: 37 | B42: Facturación y fiscalidad | C42: Facturas rectificativas en devoluciones | D42: Implementado: al liquidar un reembolso se emite sola una factura rectificativa (serie R, importes negativos, por diferencias, con la factura que rectifica y el motivo) y se envía por email. | E42: Visto bueno de la gestoría al formato | F42: Importante | G42: Implementado | H42: Gestoría / asesor fiscal | J42: Pendiente | K42: apps/server/src/plugins/invoicing (rectificativas) | L42: Con Redsys: reembolsar en el panel del banco y pulsar «Liquidar» en el reembolso del pedido.
A43: 38 | B43: Facturación y fiscalidad | C43: NIF del cliente en la factura | D43: Hoy no se pide el NIF del comprador. Puede ser necesario para clientes empresa (factura completa). | E43: Necesario solo para empresas / no necesario | F43: Importante | G43: No se pide | H43: Gestoría / asesor fiscal | J43: Pendiente | K43: Checkout + facturación (requiere desarrollo)
A44: 39 | B44: Facturación y fiscalidad | C44: Numeración de las facturas | D44: Serie única «A» con numeración continua (A-000001, A-000002…). Confirmar si vale o se quiere numeración por año. | E44: Serie A continua / A-2026-0001 … | F44: Importante | G44: A-000001 continua | H44: Gestoría / asesor fiscal | J44: Pendiente | K44: apps/server/src/plugins/invoicing/constants.ts
B45: D. Dominios, servidor y despliegue
A46: 40 | B46: Dominios, servidor y despliegue | C46: Dominio de la tienda | D46: Dirección pública de la tienda. De ella salen varias variables. | E46: ironsavage.es | F46: Crítico | G46: tienda.example.com | H46: Cliente | J46: Pendiente | K46: .env.prod → PUBLIC_DOMAIN, NEXT_PUBLIC_SITE_URL, STOREFRONT_URL, CORS_ORIGIN | L46: Debe apuntar (DNS A/AAAA) a la IP del servidor antes de arrancar.
A47: 41 | B47: Dominios, servidor y despliegue | C47: Subdominio del panel/API | D47: Subdominio para el panel de administración, la API y las imágenes. | E47: api.ironsavage.es | F47: Crítico | G47: api.tienda.example.com | H47: Cliente | J47: Pendiente | K47: .env.prod → API_DOMAIN, ASSET_URL_PREFIX, REDSYS_NOTIFICATION_URL
A48: 42 | B48: Dominios, servidor y despliegue | C48: Acceso al panel DNS del dominio | D48: Para crear los registros del dominio (servidor y correo). | E48: Usuario de acceso o persona de contacto | F48: Crítico | G48: — | H48: Cliente | J48: Pendiente | K48: (proveedor del dominio)
A49: 43 | B49: Dominios, servidor y despliegue | C49: Servidor (hosting) | D49: VPS con Docker. Ver requisitos y proveedores orientativos en la hoja «Hosting». | E49: Hetzner CX32 (4 vCPU, 8 GB) | F49: Crítico | G49: Solo en local | H49: Cliente + Técnico | J49: Pendiente | K49: docker-compose.prod.yml
A50: 44 | B50: Dominios, servidor y despliegue | C50: Email para los certificados HTTPS | D50: Solo para avisos de renovación del certificado (Let's Encrypt). | E50: sistemas@ironsavage.es | F50: Recomendado | G50: admin@example.com | H50: Cliente | J50: Pendiente | K50: .env.prod → CADDY_EMAIL
A51: 45 | B51: Dominios, servidor y despliegue | C51: Nombre de la tienda | D51: Nombre comercial en títulos de página y metadatos. | E51: Iron Savage | F51: Informativo | G51: Iron Savage | H51: Cliente | J51: Pendiente | K51: .env.prod → NEXT_PUBLIC_SITE_NAME
A52: 46 | B52: Dominios, servidor y despliegue | C52: Entorno de producción | D52: Poner en modo producción cuando todo esté listo. | E52: production | F52: Crítico | G52: test | H52: Técnico | J52: Pendiente | K52: .env.prod → APP_ENV
A53: 47 | B53: Dominios, servidor y despliegue | C53: Versión de la aplicación | D53: Número que aparece en el pie de la web. | E53: 1.0.0 en el lanzamiento | F53: Informativo | G53: 0.1.0 | H53: Técnico | J53: Pendiente | K53: package.json (raíz) → version
A54: 48 | B54: Dominios, servidor y despliegue | C54: Ejecutar el seed en producción | D54: Tras el primer despliegue (y tras actualizar), ejecutar «npm run seed»: crea zonas, categorías de IVA, el método de envío y el de pago. Es idempotente y no pisa lo editado en el panel. | E54: Hecho | F54: Crítico | G54: — | H54: Técnico | J54: Pendiente | K54: apps/server: npm run seed
B55: E. Correo electrónico (emails automáticos)
A56: 49 | B56: Correo electrónico (emails automáticos) | C56: Proveedor de envío (SMTP) | D56: Servicio que envía los emails de la tienda. Hoy no sale ningún email real (se guardan en archivo). | E56: Brevo / Amazon SES / Mailgun / Google Workspace | F56: Crítico | G56: EMAIL_PROVIDER=dev (no envía) | H56: Cliente + Técnico | J56: Pendiente | K56: .env.prod → EMAIL_PROVIDER=smtp | L56: Recomendado un proveedor transaccional si hay volumen.
A57: 50 | B57: Correo electrónico (emails automáticos) | C57: Servidor y puerto SMTP | D57: Los da el proveedor. | E57: smtp-relay.brevo.com · 587 · SMTP_SECURE=false | F57: Crítico | G57: (vacío) | H57: Cliente + Técnico | J57: Pendiente | K57: .env.prod → SMTP_HOST, SMTP_PORT, SMTP_SECURE
A58: 51 | B58: Correo electrónico (emails automáticos) | C58: Usuario SMTP | E58: usuario@ironsavage.es | F58: Crítico | G58: (vacío) | H58: Cliente | J58: Pendiente | K58: .env.prod → SMTP_USER
A59: 52 | B59: Correo electrónico (emails automáticos) | C59: Contraseña o clave API SMTP | D59: Dato confidencial: entregar por un canal seguro, nunca por email. | E59: •••••••• | F59: Crítico | G59: (vacío) | H59: Cliente | J59: Pendiente | K59: .env.prod → SMTP_PASSWORD | L59: Confidencial.
A60: 53 | B60: Correo electrónico (emails automáticos) | C60: Remitente que verá el cliente | D60: Nombre y dirección desde la que salen los emails. | E60: Iron Savage <pedidos@ironsavage.es> | F60: Crítico | G60: Iron Savage <no-reply@example.com> | H60: Cliente | J60: Pendiente | K60: .env.prod → EMAIL_FROM | L60: El dominio debe ser el mismo que el configurado en SPF/DKIM.
A61: 54 | B61: Correo electrónico (emails automáticos) | C61: Nombre comercial en los emails | D61: Nombre que aparece en asuntos, saludo y pie («Bienvenido/a a …»). Si se deja vacío, se usa la razón social. | E61: Iron Savage | F61: Importante | G61: Iron Savage | H61: Cliente | J61: Pendiente | K61: .env.prod → EMAIL_STORE_NAME
A62: 55 | B62: Correo electrónico (emails automáticos) | C62: Email de «responder a» | D62: Donde llegan las respuestas si el cliente contesta a un email automático. | E62: hola@ironsavage.es | F62: Importante | G62: soporte@example.com | H62: Cliente | J62: Pendiente | K62: .env.prod → EMAIL_REPLY_TO
A63: 56 | B63: Correo electrónico (emails automáticos) | C63: Registros SPF, DKIM y DMARC | D63: Para que los emails no acaben en spam. El proveedor de email da los valores y se añaden al DNS del dominio. | E63: Registros TXT añadidos y verificados | F63: Importante | G63: No configurado | H63: Cliente + Técnico | J63: Pendiente | K63: (DNS del dominio)
A64: 57 | B64: Correo electrónico (emails automáticos) | C64: Textos de los emails | D64: Asuntos y frases de cada email automático: ver la hoja «Textos de emails». | E64: Ver hoja | F64: Importante | G64: Textos genéricos | H64: Cliente | J64: Pendiente | K64: apps/server/src/plugins/transactional-email/templates/
B65: F. Pagos con tarjeta (Redsys)
A66: 58 | B66: Pagos con tarjeta (Redsys) | C66: Contrato de TPV Virtual con el banco | D66: Sin él no se pueden cobrar pagos reales. | E66: TPV contratado con CaixaBank (fecha) | F66: Crítico | G66: Credenciales públicas de pruebas de Redsys | H66: Banco | J66: Pendiente | K66: —
A67: 59 | B67: Pagos con tarjeta (Redsys) | C67: Código de comercio (FUC) | D67: Lo da el banco. | E67: 123456789 | F67: Crítico | G67: 999008881 (pruebas) | H67: Banco | J67: Pendiente | K67: .env.prod → REDSYS_MERCHANT_CODE
A68: 60 | B68: Pagos con tarjeta (Redsys) | C68: Número de terminal | D68: Lo da el banco. | E68: 1 | F68: Crítico | G68: 1 (pruebas) | H68: Banco | J68: Pendiente | K68: .env.prod → REDSYS_TERMINAL
A69: 61 | B69: Pagos con tarjeta (Redsys) | C69: Clave secreta SHA-256 | D69: Se obtiene en el panel de Redsys del banco. Confidencial. | E69: •••••••• | F69: Crítico | G69: Clave pública de pruebas | H69: Banco | J69: Pendiente | K69: .env.prod → REDSYS_SECRET_KEY | L69: Confidencial.
A70: 62 | B70: Pagos con tarjeta (Redsys) | C70: Modo «Conexión por Redirección» | D70: Confirmar con el banco que el terminal admite este método (es el que usa la tienda). | E70: Confirmado por el banco | F70: Importante | G70: — | H70: Banco | J70: Pendiente | K70: —
A71: 63 | B71: Pagos con tarjeta (Redsys) | C71: Pasar Redsys a producción | D71: Cuando todo esté probado con una compra real. | E71: production | F71: Crítico | G71: test | H71: Técnico | J71: Pendiente | K71: .env.prod → REDSYS_ENVIRONMENT
B72: G. Accesos y claves internas
A73: 64 | B73: Accesos y claves internas | C73: Usuario del superadministrador | D73: Usuario principal del panel de administración. | E73: admin.ironsavage | F73: Crítico | G73: superadmin | H73: Cliente | J73: Pendiente | K73: .env.prod → SUPERADMIN_USERNAME
A74: 65 | B74: Accesos y claves internas | C74: Contraseña del superadministrador | D74: Contraseña fuerte y única. Confidencial. | E74: •••••••• | F74: Crítico | G74: superadmin (solo pruebas) | H74: Cliente | J74: Pendiente | K74: .env.prod → SUPERADMIN_PASSWORD | L74: Confidencial.
A75: 66 | B75: Accesos y claves internas | C75: Otras personas con acceso al panel | D75: Empleados, almacén, gestoría… con permisos limitados. | E75: Almacén: solo pedidos; Gestoría: solo facturas | F75: Recomendado | G75: Solo 1 superadmin | H75: Cliente | J75: Pendiente | K75: Dashboard → Ajustes → Administradores
A76: 67 | B76: Accesos y claves internas | C76: Claves técnicas internas | D76: Se generan automáticamente al desplegar; el cliente no tiene que aportar nada. | E76: — | F76: Informativo | G76: replace-with-… | H76: Técnico | J76: Pendiente | K76: .env.prod → COOKIE_SECRET, DB_PASSWORD, REVALIDATION_SECRET
B77: H. Envíos y logística
A78: 68 | B78: Envíos y logística | C78: Tarifas de envío reales | D78: Hay un método «Envío estándar» (5 € + IVA, península y Baleares) como valor provisional. En cada método se marca a qué territorios aplica y un pedido mínimo opcional, así que las tarifas se configuran sin programar. | E78: Península 4,95 €; Baleares 9,95 € | F78: Crítico | G78: 5 € + IVA (península y Baleares) | H78: Cliente | J78: Pendiente | K78: Dashboard → Ajustes → Métodos de envío | L78: Ejemplos en docs/iva-envios-facturacion.md.
A79: 69 | B79: Envíos y logística | C79: Nombre del método de envío | D79: Ya renombrado a «Envío estándar» (antes «Standard Shipping»). Cambiarlo si se quiere indicar el plazo o el transportista. | E79: Envío estándar (24-72 h) | F79: Informativo | G79: Envío estándar | H79: Cliente | J79: Pendiente | K79: Dashboard → Ajustes → Métodos de envío
A80: 70 | B80: Envíos y logística | C80: Envío gratis a partir de un importe | D80: Preparado: basta con crear un método de 0 € con la condición «Territorios de España y pedido mínimo» y el importe mínimo. | E80: Gratis a partir de 50 € (o «No») | F80: Recomendado | G80: No configurado | H80: Cliente | J80: Pendiente | K80: Dashboard → Ajustes → Métodos de envío | L80: Si se activa, se puede anunciar en la barra superior.
A81: 71 | B81: Envíos y logística | C81: Zonas / países a los que se envía | D81: Península y Baleares activadas; Canarias, Ceuta y Melilla preparadas pero desactivadas. Fuera de España no se envía. La FAQ dice «Por ahora solo enviamos a España». | E81: Península y Baleares | F81: Importante | G81: Península y Baleares | H81: Cliente | J81: Pendiente | K81: Dashboard → Métodos de envío (territorios) y features/products/messages (FAQ)
A82: 72 | B82: Envíos y logística | C82: Remitente en la etiqueta de envío | D82: La etiqueta imprimible solo lleva el destinatario. Algunos transportistas exigen remitente. | E82: Sí, con la dirección del almacén / No hace falta | F82: Recomendado | G82: Sin remitente | H82: Cliente | J82: Pendiente | K82: apps/server/src/plugins/order-tools/order-tools.service.ts | L82: Pequeño desarrollo si se quiere.
A83: 73 | B83: Envíos y logística | C83: Email «pedido enviado» con número de seguimiento | D83: Hoy no existe: el cliente ve el estado en «Mi cuenta», pero no recibe email al enviarse. | E83: Sí / No | F83: Recomendado | G83: No existe | H83: Cliente | J83: Pendiente | K83: transactional-email (requiere desarrollo) | L83: Pequeño desarrollo si se quiere.
B84: I. Textos de la tienda (marketing)
A85: 74 | B85: Textos de la tienda (marketing) | C85: Mensajes de la barra superior | D85: Tres avisos fijos arriba de todas las páginas. Deben ser ciertos. | E85: Envío en 24-72 h · Pago seguro con Redsys · Acumula puntos | F85: Importante | G85: Envío rápido · Pago seguro con Redsys · Acumula puntos en tus compras | H85: Cliente | J85: Pendiente | K85: apps/storefront/src/site/navigation/top-bar-messages.ts | L85: Incluye versión en inglés.
A86: 75 | B86: Textos de la tienda (marketing) | C86: Portada: título y subtítulo | D86: Lo primero que se ve en la home. | E86: Entrena Savage · Suplementación deportiva premium para… | F86: Recomendado | G86: Entrena Savage · Suplementación deportiva premium para atletas que entrenan duro… | H86: Cliente | J86: Pendiente | K86: apps/storefront/src/site/home/messages/es.json → Hero
A87: 76 | B87: Textos de la tienda (marketing) | C87: Portada: las 3 ventajas | D87: «Calidad rigurosa: cada lote seleccionado por pureza y rendimiento», «Precios justos», «Entrega rápida». Hay que poder demostrar lo que se afirma (publicidad). | E87: Textos confirmados o nuevos | F87: Importante | G87: Calidad rigurosa / Precios justos / Entrega rápida | H87: Cliente | J87: Pendiente | K87: apps/storefront/src/site/home/messages/es.json → Home.features
A88: 77 | B88: Textos de la tienda (marketing) | C88: Descripción para Google (general) | D88: Descripción por defecto en buscadores. Hoy es texto de plantilla genérico. | E88: Suplementación deportiva premium: proteína, creatina y pre-entreno. Envío en 24-72 h. | F88: Importante | G88: Compra los mejores productos en Iron Savage. Productos de calidad, precios competitivos y entrega rápida. | H88: Cliente | J88: Pendiente | K88: apps/storefront/src/platform/i18n/messages/es.json → Common.siteDescription | L88: Máx. ~155 caracteres.
A89: 78 | B89: Textos de la tienda (marketing) | C89: Descripción para Google (portada) | E89: Texto de hasta ~155 caracteres | F89: Recomendado | G89: Iron Savage: suplementación deportiva premium para atletas que entrenan duro… | H89: Cliente | J89: Pendiente | K89: apps/storefront/src/site/home/messages/es.json → Home.description
A90: 79 | B90: Textos de la tienda (marketing) | C90: Texto del pie de página | D90: Frase bajo el logo en el pie. | E90: Frase de marca | F90: Informativo | G90: Suplementación deportiva premium para atletas que entrenan duro… | H90: Cliente | J90: Pendiente | K90: apps/storefront/src/site/messages/es.json → Footer.description
A91: 80 | B91: Textos de la tienda (marketing) | C91: Preguntas frecuentes de producto | D91: Se han reescrito con texto veraz y neutro (la plantilla prometía envíos a 50 países, 30 días de devolución y envío exprés). Ampliar con datos reales si se quiere. | E91: Textos confirmados | F91: Importante | G91: Texto neutro que remite a «Envíos y devoluciones» | H91: Cliente | J91: Pendiente | K91: apps/storefront/src/features/products/messages/es.json → Product.faq
A92: 81 | B92: Textos de la tienda (marketing) | C92: Sellos de confianza en la ficha de producto | D92: Envío rápido · Desistimiento en 14 días · Pago seguro · Garantía legal de 3 años. | E92: Confirmado / cambios | F92: Recomendado | G92: Corregidos (antes: «Devoluciones gratuitas», «Garantía de 30 días») | H92: Cliente | J92: Pendiente | K92: apps/storefront/src/features/products/messages/es.json → Product.trustBadges
A93: 82 | B93: Textos de la tienda (marketing) | C93: Versión en inglés de todos los textos | D93: Cada texto anterior tiene su equivalente en inglés. | E93: Traducciones revisadas | F93: Recomendado | G93: Traducción propia | H93: Cliente | J93: Pendiente | K93: Mismos archivos, en.json
B94: J. Marca e imágenes
A95: 83 | B95: Marca e imágenes | C95: Icono de la pestaña del navegador (favicon) | D95: Ya generado a partir del monograma «IS» del logo. Solo cambiar si se quiere otro. | E95: Confirmado / PNG 512×512 nuevo | F95: Informativo | G95: Monograma IS (generado) | H95: Cliente | J95: Pendiente | K95: apps/storefront/src/app/[locale]/favicon.ico e icon.png
A96: 84 | B96: Marca e imágenes | C96: Icono para móviles (Apple / accesos directos) | D96: Ya generado a partir del logo. | E96: Confirmado / PNG 180×180 nuevo | F96: Informativo | G96: Generado | H96: Cliente | J96: Pendiente | K96: apps/storefront/src/app/[locale]/apple-icon.png
A97: 85 | B97: Marca e imágenes | C97: Imagen para compartir en redes sociales | D97: Ya generada (logo completo sobre fondo negro). Se usa en toda página sin foto propia. | E97: Confirmado / JPG-PNG 1200×630 nuevo | F97: Informativo | G97: Generada | H97: Cliente | J97: Pendiente | K97: apps/storefront/public/og-image.png
A98: 86 | B98: Marca e imágenes | C98: Logo definitivo | D98: Ya integrado en la web, los emails y las facturas. Confirmar que es la versión final. | E98: Confirmado | F98: Informativo | G98: Logo Iron Savage | H98: Cliente | J98: Pendiente | K98: apps/storefront/src/assets/, email (logo-asset.ts), factura (logo-base64.ts)
A99: 87 | B99: Marca e imágenes | C99: Archivos sobrantes de la plantilla | D99: public/next.svg y public/vendure.svg ya se han borrado. | E99: — | F99: Informativo | G99: Borrados | H99: Técnico | J99: Pendiente | K99: apps/storefront/public/
B100: K. Analítica (Google Analytics 4)
...

Sheet Textos de emails
A1: Email | B1: Cuándo se envía | C1: Asunto actual | D1: Frases clave actuales | E1: Qué conviene revisar | F1: TEXTO NUEVO (opcional) | G1: Archivo (apps/server/src/plugins/transactional-email/)
A2: Verifica tu email | B2: Al registrarse en la tienda | C2: Verifica tu email en {tienda} | D2: Gracias por registrarte en {tienda}. Confirma tu dirección de email para activar tu cuenta. | E2: Tono y texto del botón. | G2: templates/email-verification.ts
A3: Activa tu cuenta | B3: Cuando un administrador crea la cuenta de un cliente o atleta | C3: Activa tu cuenta en {tienda} | D3: Te hemos creado una cuenta en {tienda}. Para activarla, confirma tu email y elige tu contraseña. | E3: Tono. | G3: templates/email-verification.ts
A4: Bienvenida | B4: Al verificar la cuenta | C4: Bienvenido/a a {tienda} | D4: Tu cuenta en {tienda} ha sido verificada correctamente. ¡Ya puedes comprar con tu cuenta! · Gracias por registrarte. | E4: Se puede añadir un mensaje de bienvenida o un cupón de primera compra. | G4: templates/registration-confirmation.ts
A5: Recupera tu contraseña | B5: Al pedir «He olvidado mi contraseña» | C5: Recupera tu contraseña en {tienda} | D5: Hemos recibido una solicitud para restablecer la contraseña de tu cuenta en {tienda}. | E5: Tono. | G5: templates/password-reset.ts
A6: Crea tu contraseña | B6: Cuando un administrador verifica una cuenta y envía el enlace | C6: Crea tu contraseña en {tienda} | D6: Tu cuenta en {tienda} ya está activa. Solo falta que elijas tu contraseña para poder iniciar sesión. | E6: Tono. | G6: templates/password-reset.ts
A7: Pedido recibido | B7: Al iniciar el pago | C7: Hemos recibido tu pedido #CÓDIGO | D7: Hemos recibido tu pedido… (con el resumen de productos) | E7: Tono. | G7: templates/order-received.ts
A8: Pago confirmado | B8: Cuando Redsys confirma el cobro | C8: Pago confirmado — pedido #CÓDIGO | D8: Hemos confirmado el pago de tu pedido… Prepararemos tu pedido para el envío en breve. | E8: Poner un plazo concreto de preparación/envío en lugar de «en breve». | G8: templates/payment-confirmed.ts
A9: Pedido cancelado | B9: Al cancelar un pedido desde el panel | C9: Pedido cancelado — #CÓDIGO | D9: Tu pedido … ha sido cancelado. Si crees que se trata de un error, contáctanos. | E9: Falta cómo contactar: añadir el email o el teléfono de atención al cliente. Indicar el plazo del reembolso. | G9: templates/order-cancelled.ts
A10: Factura disponible | B10: Al generarse la factura (pago confirmado) | C10: Factura A-000001 disponible | D10: Ya tienes disponible la factura… También puedes descargarla en cualquier momento desde tu cuenta. | E10: Tono. | G10: templates/invoice-available.ts
A11: Reenvío de factura | B11: Cuando un administrador reenvía la factura | C11: Factura A-000001 — pedido #CÓDIGO | D11: Te reenviamos la factura … correspondiente al pedido … La encontrarás adjunta a este email en PDF. | E11: Tono. | G11: templates/invoice-resend.ts
A12: Factura rectificativa | B12: Al liquidar un reembolso | C12: Factura rectificativa R-000001 — pedido #CÓDIGO | D12: Hemos tramitado un reembolso de tu pedido… Te adjuntamos la factura rectificativa…, que corrige la factura… por el importe reembolsado. | E12: Tono; plazo en que llega el dinero. | G12: templates/credit-note-available.ts
A13: Pie común de todos los emails | B13: En todos | C13: — | D13: {tienda} — este es un email transaccional automático, por favor no respondas si no tienes una duda relacionada. · Ir a la tienda · Mi cuenta · © {año} {tienda} | E13: La frase es confusa (¿se puede responder o no?): decidir según EMAIL_REPLY_TO. Recomendado añadir razón social, dirección y enlace a la política de privacidad. | G13: templates/layout.ts
A14: Pedido enviado (no existe) | B14: — | C14: — | D14: — | E14: Decidir si se quiere un email al enviar el pedido, con transportista y número de seguimiento (requiere desarrollo). | G14: —
A16: {tienda} = nombre comercial (EMAIL_STORE_NAME). #CÓDIGO = código del pedido. Todos los emails llevan el logo, los colores de la marca y enlaces a la tienda y a «Mi cuenta».

Sheet Hosting
B1: Dónde alojar la tienda — recomendaciones
B3: La aplicación son 4 piezas que corren juntas con Docker en un único servidor (ya preparado, ver docker-compose.prod.yml): base de datos (PostgreSQL), servidor Vendure (API + panel de administración), worker (tareas en segundo plano: emails, facturas...) y la tienda (Next.js) — más un proxy (Caddy) que da el certificado HTTPS gratis y automático. No hace falta contratar la base de datos por separado.
B5: Requisitos imprescindibles (no negociables)
B6: • Soporte para Docker y Docker Compose
B7: • IP pública fija, con capacidad de abrir los puertos 80 y 443
B8: • Almacenamiento persistente (volúmenes en disco) — las fotos de producto y las facturas en PDF se guardan en disco; se perderían en un hosting "sin estado" tipo serverless puro
B9: • Acceso administrador/SSH al servidor
B11: Specs mínimas recomendadas para el servidor
B12: Recurso | C12: Mínimo | D12: Recomendado (con margen) | E12: Notas
B13: CPU | C13: 2 vCPU | D13: 4 vCPU
B14: RAM | C14: 4 GB | D14: 8 GB
B15: Disco | C15: 40 GB SSD | D15: 80 GB SSD | E15: Crece con catálogo, facturas y backups
B16: Sistema operativo | C16: Linux (Ubuntu 22.04/24.04 LTS) + Docker | D16: Igual
B17: Red | C17: IP pública fija, puertos 80/443 abiertos | D17: Igual
B18: Ancho de banda | C18: Según tráfico esperado | D18: La mayoría de VPS incluyen varios TB/mes
B19: Snapshot del proveedor | C19: Opcional | D19: Recomendable, además del backup propio de la app
B21: Proveedores de servidor orientativos (ejemplos, sin compromiso)
B22: Proveedor | C22: Tipo | D22: Precio orientativo/mes | E22: Notas
B23: Hetzner Cloud | C23: VPS Europa | D23: 15-25 € | E23: Buena relación calidad-precio, datacenters en Alemania/Finlandia
B24: DigitalOcean | C24: VPS | D24: 24-48 $ | E24: Interfaz sencilla, buena documentación
B25: OVHcloud | C25: VPS Europa (España/Francia) | D25: 15-30 € | E25: Proveedor europeo, facturación en español
B26: Contabo | C26: VPS | D26: 10-20 € | E26: Más barato, algo menos de soporte
B27: AWS Lightsail / Google Cloud | C27: VPS gestionado | D27: Desde ~20 $ | E27: Más flexible para escalar más adelante, curva de aprendizaje mayor
B29: Almacenamiento externo para backups (recomendado, opcional)
B30: Proveedor | C30: Precio orientativo | D30: Notas
B31: Backblaze B2 | C31: ~5 $/TB/mes | D31: Barato, compatible con S3
B32: Amazon S3 | C32: Variable | D32: Estándar de la industria
B33: Wasabi | C33: ~7 $/TB/mes | D33: Sin coste de salida de datos
B35: Nota: si en el futuro crece mucho el volumen de pedidos, la base de datos se puede separar a un servicio gestionado (ej. Amazon RDS, DigitalOcean Managed Postgres) sin cambios grandes en el código — no hace falta decidirlo ahora.
